sopel_reddit/__init__.py
sopel_reddit-1.1.0.dist-info/COPYING
sopel_reddit-1.1.0.dist-info/METADATA
sopel_reddit-1.1.0.dist-info/WHEEL
sopel_reddit-1.1.0.dist-info/entry_points.txt
sopel_reddit-1.1.0.dist-info/top_level.txt
sopel_reddit-1.1.0.dist-info/RECORD
