Metadata-Version: 2.1
Name: sopel-reddit
Version: 1.1.0
Summary: A reddit plugin for Sopel IRC bots.
Home-page: https://github.com/sopel-irc/sopel-reddit
Author: dgw
Author-email: dgw@technobabbl.es
License: Eiffel Forum License, version 2
Classifier: Intended Audience :: Developers
Classifier: Intended Audience :: System Administrators
Classifier: License :: Eiffel Forum License (EFL)
Classifier: License :: OSI Approved :: Eiffel Forum License
Classifier: Topic :: Communications :: Chat :: Internet Relay Chat
License-File: COPYING
Requires-Dist: sopel <9,>=8.0.0.dev0
Requires-Dist: praw <8.0.0,>=4.0.0
